balena/__init__.py
balena/embeddings.py
balena/hci.py
balena_cpu-1.0.0.dist-info/LICENSE
balena_cpu-1.0.0.dist-info/METADATA
balena_cpu-1.0.0.dist-info/WHEEL
balena_cpu-1.0.0.dist-info/top_level.txt
balena_cpu-1.0.0.dist-info/RECORD
