Metadata-Version: 2.1
Name: balena-cpu
Version: 1.0.0
Summary: BALanced Execution through Natural Activation : a human-computer interaction methodology for code running.
Keywords: transformers,speech-recognition,text-extraction,execution,speech-to-text,NLP,sentence-similarity,speech-to-function,sentence-transformers,wav2vec2
Classifier: Programming Language :: Python
Classifier: Programming Language :: Python :: 3
Classifier: Intended Audience :: Education
Classifier: Intended Audience :: Science/Research
Classifier: License :: OSI Approved :: Apache Software License
Classifier: Topic :: Scientific/Engineering
Classifier: Topic :: Scientific/Engineering :: Artificial Intelligence
Classifier: Topic :: Software Development
Classifier: Topic :: Software Development :: Libraries
Classifier: Topic :: Software Development :: Libraries :: Python Modules
License-File: LICENSE
